jrpygcloudml/__init__.py
jrpygcloudml/__version__.py
jrpygcloudml-0.1.1.dist-info/WHEEL
jrpygcloudml-0.1.1.dist-info/METADATA
jrpygcloudml-0.1.1.dist-info/RECORD
